hypermodern_python/__init__.py
hypermodern_python/console.py
hypermodern_python/wikipedia.py
hypermodern_python_mikeh-0.1.0.dist-info/entry_points.txt
hypermodern_python_mikeh-0.1.0.dist-info/LICENSE
hypermodern_python_mikeh-0.1.0.dist-info/WHEEL
hypermodern_python_mikeh-0.1.0.dist-info/METADATA
hypermodern_python_mikeh-0.1.0.dist-info/RECORD
