Metadata-Version: 2.1
Name: hypermodern-python-mikeh
Version: 0.1.0
Summary: Hypermodern Python Project
Home-page: https://github.com/MichaelHarrison87/hypermodern-mikeh
Keywords: hypermodern
Author: MichaelHarrison87
Author-email: harrisoneighty7@gmail.com
Requires-Python: >=3.7,<4.0
Classifier: Programming Language :: Python :: 3
Classifier: Programming Language :: Python :: 3.7
Classifier: Programming Language :: Python :: 3.8
Requires-Dist: click (>=8.0.3,<9.0.0)
Requires-Dist: desert (>=2020.11.18,<2021.0.0)
Requires-Dist: marshmallow (>=3.14.1,<4.0.0)
Requires-Dist: requests (>=2.27.1,<3.0.0)
Project-URL: Repository, https://github.com/MichaelHarrison87/hypermodern-mikeh
